<?xml version="1.0" encoding="utf-8"?>
<class id="205e5666-404f-4b0c-89c5-41fd7d8a36e8" type="Folder" typeId="3407a825-1331-4f3f-89a4-901903ed97ce">
  <name>Templates</name>
  <display>Templates</display>
  <isAbstract>false</isAbstract>
  <sort-children>by-type-then-by-name</sort-children>
  <genericTypes />
  <isMapped>false</isMapped>
  <parentFolderId>e8ee9f41-d5b2-4a78-b2bb-281a4c60a3ae</parentFolderId>
  <packageId>8d838a3c-f5ed-4c5e-bae9-b366a4869881</packageId>
  <packageName>Intent.Modules.NET</packageName>
  <stereotypes>
    <stereotype stereotypeDefinitionId="61132551-825d-4c6e-b9f1-0f95249d08d4" name="Folder Options">
      <addedByDefault>true</addedByDefault>
      <definitionPackageName>Intent.VisualStudio.Projects</definitionPackageName>
      <definitionPackageId>a0636ab7-d3a1-430b-9609-11a18aa3cc7f</definitionPackageId>
      <properties>
        <property name="4bfbefd0-d22e-4ca0-9723-92ae273feca4" display="Namespace Provider" value="true" isActive="true" />
      </properties>
    </stereotype>
  </stereotypes>
  <metadata />
  <childElements>
    <childElement id="5cbc5198-7ed4-4066-add4-561ec7c61411" type="Template Output" typeId="d421c322-7a51-4094-89fa-e5d8a0a97b27">
      <name>Intent.ModuleBuilder.CSharp.Templates.CSharpStringInterpolationTemplate</name>
      <display>Intent.ModuleBuilder.CSharp.Templates.CSharpStringInterpolationTemplate</display>
      <externalReference>Intent.ModuleBuilder.CSharp</externalReference>
      <isAbstract>false</isAbstract>
      <genericTypes />
      <isMapped>false</isMapped>
      <parentFolderId>205e5666-404f-4b0c-89c5-41fd7d8a36e8</parentFolderId>
      <packageId>8d838a3c-f5ed-4c5e-bae9-b366a4869881</packageId>
      <packageName>Intent.Modules.NET</packageName>
      <stereotypes>
        <stereotype stereotypeDefinitionId="967ae6f6-cc06-4b67-a391-44ed1aac1959" name="Template Output Settings">
          <addedByDefault>true</addedByDefault>
          <definitionPackageName>Intent.VisualStudio.Projects</definitionPackageName>
          <definitionPackageId>a0636ab7-d3a1-430b-9609-11a18aa3cc7f</definitionPackageId>
          <properties>
            <property name="2ae1addc-b4dc-4cc8-94e1-56ef8a5420aa" display="Is Enabled" value="true" isActive="true" />
            <property name="2d8e6d2c-785c-4708-9104-bd3e9781a86a" display="Registration Filter" isActive="true" />
          </properties>
        </stereotype>
      </stereotypes>
      <metadata>
        <entry key="status" value="assigned" />
      </metadata>
      <childElements />
    </childElement>
    <childElement id="9c95ef9e-5b74-4909-b9ac-934fafc0cf9d" type="Template Output" typeId="d421c322-7a51-4094-89fa-e5d8a0a97b27">
      <name>Intent.ModuleBuilder.CSharp.Templates.CSharpT4Template</name>
      <display>Intent.ModuleBuilder.CSharp.Templates.CSharpT4Template</display>
      <externalReference>Intent.ModuleBuilder.CSharp</externalReference>
      <isAbstract>false</isAbstract>
      <genericTypes />
      <isMapped>false</isMapped>
      <parentFolderId>205e5666-404f-4b0c-89c5-41fd7d8a36e8</parentFolderId>
      <packageId>8d838a3c-f5ed-4c5e-bae9-b366a4869881</packageId>
      <packageName>Intent.Modules.NET</packageName>
      <stereotypes>
        <stereotype stereotypeDefinitionId="967ae6f6-cc06-4b67-a391-44ed1aac1959" name="Template Output Settings">
          <addedByDefault>true</addedByDefault>
          <definitionPackageName>Intent.VisualStudio.Projects</definitionPackageName>
          <definitionPackageId>a0636ab7-d3a1-430b-9609-11a18aa3cc7f</definitionPackageId>
          <properties>
            <property name="2ae1addc-b4dc-4cc8-94e1-56ef8a5420aa" display="Is Enabled" value="true" isActive="true" />
            <property name="2d8e6d2c-785c-4708-9104-bd3e9781a86a" display="Registration Filter" isActive="true" />
          </properties>
        </stereotype>
      </stereotypes>
      <metadata>
        <entry key="status" value="assigned" />
      </metadata>
      <childElements />
    </childElement>
    <childElement id="9a942d06-245a-4018-ae84-6a1b99df32c3" type="Template Output" typeId="d421c322-7a51-4094-89fa-e5d8a0a97b27">
      <name>Intent.ModuleBuilder.CSharp.Templates.CSharpTemplate.T4Template.PreProcessed</name>
      <display>Intent.ModuleBuilder.CSharp.Templates.CSharpTemplate.T4Template.PreProcessed</display>
      <externalReference>Intent.ModuleBuilder.CSharp</externalReference>
      <isAbstract>false</isAbstract>
      <genericTypes />
      <isMapped>false</isMapped>
      <parentFolderId>205e5666-404f-4b0c-89c5-41fd7d8a36e8</parentFolderId>
      <packageId>8d838a3c-f5ed-4c5e-bae9-b366a4869881</packageId>
      <packageName>Intent.Modules.NET</packageName>
      <stereotypes>
        <stereotype stereotypeDefinitionId="967ae6f6-cc06-4b67-a391-44ed1aac1959" name="Template Output Settings">
          <addedByDefault>true</addedByDefault>
          <definitionPackageName>Intent.VisualStudio.Projects</definitionPackageName>
          <definitionPackageId>a0636ab7-d3a1-430b-9609-11a18aa3cc7f</definitionPackageId>
          <properties>
            <property name="2ae1addc-b4dc-4cc8-94e1-56ef8a5420aa" display="Is Enabled" value="true" isActive="true" />
            <property name="2d8e6d2c-785c-4708-9104-bd3e9781a86a" display="Registration Filter" isActive="true" />
          </properties>
        </stereotype>
      </stereotypes>
      <metadata>
        <entry key="status" value="assigned" />
      </metadata>
      <childElements />
    </childElement>
    <childElement id="c9fcc5c2-0c60-4972-905f-52fc6300de02" type="Template Output" typeId="d421c322-7a51-4094-89fa-e5d8a0a97b27">
      <name>Intent.ModuleBuilder.CSharp.Templates.CSharpTemplatePartial</name>
      <display>Intent.ModuleBuilder.CSharp.Templates.CSharpTemplatePartial</display>
      <externalReference>Intent.ModuleBuilder.CSharp</externalReference>
      <isAbstract>false</isAbstract>
      <genericTypes />
      <isMapped>false</isMapped>
      <parentFolderId>205e5666-404f-4b0c-89c5-41fd7d8a36e8</parentFolderId>
      <packageId>8d838a3c-f5ed-4c5e-bae9-b366a4869881</packageId>
      <packageName>Intent.Modules.NET</packageName>
      <stereotypes>
        <stereotype stereotypeDefinitionId="967ae6f6-cc06-4b67-a391-44ed1aac1959" name="Template Output Settings">
          <addedByDefault>true</addedByDefault>
          <definitionPackageName>Intent.VisualStudio.Projects</definitionPackageName>
          <definitionPackageId>a0636ab7-d3a1-430b-9609-11a18aa3cc7f</definitionPackageId>
          <properties>
            <property name="2ae1addc-b4dc-4cc8-94e1-56ef8a5420aa" display="Is Enabled" value="true" isActive="true" />
            <property name="2d8e6d2c-785c-4708-9104-bd3e9781a86a" display="Registration Filter" isActive="true" />
          </properties>
        </stereotype>
      </stereotypes>
      <metadata>
        <entry key="status" value="assigned" />
      </metadata>
      <childElements />
    </childElement>
    <childElement id="f789ec4d-38ff-4e58-b092-4c422e5bbdfc" type="Template Output" typeId="d421c322-7a51-4094-89fa-e5d8a0a97b27">
      <name>Intent.ModuleBuilder.CSharp.Templates.RazorStringInterpolationTemplate</name>
      <display>Intent.ModuleBuilder.CSharp.Templates.RazorStringInterpolationTemplate</display>
      <externalReference>Intent.ModuleBuilder.CSharp</externalReference>
      <isAbstract>false</isAbstract>
      <genericTypes />
      <isMapped>false</isMapped>
      <parentFolderId>205e5666-404f-4b0c-89c5-41fd7d8a36e8</parentFolderId>
      <packageId>8d838a3c-f5ed-4c5e-bae9-b366a4869881</packageId>
      <packageName>Intent.Modules.NET</packageName>
      <stereotypes>
        <stereotype stereotypeDefinitionId="967ae6f6-cc06-4b67-a391-44ed1aac1959" name="Template Output Settings">
          <addedByDefault>true</addedByDefault>
          <definitionPackageName>Intent.VisualStudio.Projects</definitionPackageName>
          <definitionPackageId>a0636ab7-d3a1-430b-9609-11a18aa3cc7f</definitionPackageId>
          <properties>
            <property name="2ae1addc-b4dc-4cc8-94e1-56ef8a5420aa" display="Is Enabled" value="true" isActive="true" />
            <property name="2d8e6d2c-785c-4708-9104-bd3e9781a86a" display="Registration Filter" isActive="true" />
          </properties>
        </stereotype>
      </stereotypes>
      <metadata>
        <entry key="status" value="assigned" />
      </metadata>
      <childElements />
    </childElement>
    <childElement id="6a2a8d64-6ffd-48fa-88aa-43dc21254867" type="Template Output" typeId="d421c322-7a51-4094-89fa-e5d8a0a97b27">
      <name>Intent.ModuleBuilder.CSharp.Templates.RazorTemplatePartial</name>
      <display>Intent.ModuleBuilder.CSharp.Templates.RazorTemplatePartial</display>
      <externalReference>Intent.ModuleBuilder.CSharp</externalReference>
      <isAbstract>false</isAbstract>
      <genericTypes />
      <isMapped>false</isMapped>
      <parentFolderId>205e5666-404f-4b0c-89c5-41fd7d8a36e8</parentFolderId>
      <packageId>8d838a3c-f5ed-4c5e-bae9-b366a4869881</packageId>
      <packageName>Intent.Modules.NET</packageName>
      <stereotypes>
        <stereotype stereotypeDefinitionId="967ae6f6-cc06-4b67-a391-44ed1aac1959" name="Template Output Settings">
          <addedByDefault>true</addedByDefault>
          <definitionPackageName>Intent.VisualStudio.Projects</definitionPackageName>
          <definitionPackageId>a0636ab7-d3a1-430b-9609-11a18aa3cc7f</definitionPackageId>
          <properties>
            <property name="2ae1addc-b4dc-4cc8-94e1-56ef8a5420aa" display="Is Enabled" value="true" isActive="true" />
            <property name="2d8e6d2c-785c-4708-9104-bd3e9781a86a" display="Registration Filter" isActive="true" />
          </properties>
        </stereotype>
      </stereotypes>
      <metadata>
        <entry key="status" value="assigned" />
      </metadata>
      <childElements />
    </childElement>
    <childElement id="60cd7be2-feb9-46b7-8f6b-7cd22b3f3c9e" type="Template Output" typeId="d421c322-7a51-4094-89fa-e5d8a0a97b27">
      <name>Intent.ModuleBuilder.ProjectItemTemplate.Partial</name>
      <display>Intent.ModuleBuilder.ProjectItemTemplate.Partial</display>
      <externalReference>Intent.ModuleBuilder</externalReference>
      <isAbstract>false</isAbstract>
      <genericTypes />
      <isMapped>false</isMapped>
      <parentFolderId>205e5666-404f-4b0c-89c5-41fd7d8a36e8</parentFolderId>
      <packageId>8d838a3c-f5ed-4c5e-bae9-b366a4869881</packageId>
      <packageName>Intent.Modules.NET</packageName>
      <stereotypes>
        <stereotype stereotypeDefinitionId="967ae6f6-cc06-4b67-a391-44ed1aac1959" name="Template Output Settings">
          <addedByDefault>true</addedByDefault>
          <definitionPackageName>Intent.VisualStudio.Projects</definitionPackageName>
          <definitionPackageId>a0636ab7-d3a1-430b-9609-11a18aa3cc7f</definitionPackageId>
          <properties>
            <property name="2ae1addc-b4dc-4cc8-94e1-56ef8a5420aa" display="Is Enabled" value="true" isActive="true" />
            <property name="2d8e6d2c-785c-4708-9104-bd3e9781a86a" display="Registration Filter" isActive="true" />
          </properties>
        </stereotype>
      </stereotypes>
      <metadata>
        <entry key="status" value="assigned" />
      </metadata>
      <childElements />
    </childElement>
    <childElement id="b3c699a8-c07e-4e1d-a0f6-2673f049013c" type="Template Output" typeId="d421c322-7a51-4094-89fa-e5d8a0a97b27">
      <name>Intent.ModuleBuilder.ProjectItemTemplate.T4Template.PreProcessed</name>
      <display>Intent.ModuleBuilder.ProjectItemTemplate.T4Template.PreProcessed</display>
      <externalReference>Intent.ModuleBuilder</externalReference>
      <isAbstract>false</isAbstract>
      <genericTypes />
      <isMapped>false</isMapped>
      <parentFolderId>205e5666-404f-4b0c-89c5-41fd7d8a36e8</parentFolderId>
      <packageId>8d838a3c-f5ed-4c5e-bae9-b366a4869881</packageId>
      <packageName>Intent.Modules.NET</packageName>
      <stereotypes>
        <stereotype stereotypeDefinitionId="967ae6f6-cc06-4b67-a391-44ed1aac1959" name="Template Output Settings">
          <addedByDefault>true</addedByDefault>
          <definitionPackageName>Intent.VisualStudio.Projects</definitionPackageName>
          <definitionPackageId>a0636ab7-d3a1-430b-9609-11a18aa3cc7f</definitionPackageId>
          <properties>
            <property name="2ae1addc-b4dc-4cc8-94e1-56ef8a5420aa" display="Is Enabled" value="true" isActive="true" />
            <property name="2d8e6d2c-785c-4708-9104-bd3e9781a86a" display="Registration Filter" isActive="true" />
          </properties>
        </stereotype>
      </stereotypes>
      <metadata>
        <entry key="status" value="assigned" />
      </metadata>
      <childElements />
    </childElement>
    <childElement id="39f7fb36-4ed6-4216-bbe7-9631e0d04fe3" type="Template Output" typeId="d421c322-7a51-4094-89fa-e5d8a0a97b27">
      <name>Intent.ModuleBuilder.TemplateRegistration.Custom</name>
      <display>Intent.ModuleBuilder.TemplateRegistration.Custom</display>
      <externalReference>Intent.ModuleBuilder</externalReference>
      <isAbstract>false</isAbstract>
      <genericTypes />
      <isMapped>false</isMapped>
      <parentFolderId>205e5666-404f-4b0c-89c5-41fd7d8a36e8</parentFolderId>
      <packageId>8d838a3c-f5ed-4c5e-bae9-b366a4869881</packageId>
      <packageName>Intent.Modules.NET</packageName>
      <stereotypes>
        <stereotype stereotypeDefinitionId="967ae6f6-cc06-4b67-a391-44ed1aac1959" name="Template Output Settings">
          <addedByDefault>true</addedByDefault>
          <definitionPackageName>Intent.VisualStudio.Projects</definitionPackageName>
          <definitionPackageId>a0636ab7-d3a1-430b-9609-11a18aa3cc7f</definitionPackageId>
          <properties>
            <property name="2ae1addc-b4dc-4cc8-94e1-56ef8a5420aa" display="Is Enabled" value="true" isActive="true" />
            <property name="2d8e6d2c-785c-4708-9104-bd3e9781a86a" display="Registration Filter" isActive="true" />
          </properties>
        </stereotype>
      </stereotypes>
      <metadata>
        <entry key="status" value="assigned" />
      </metadata>
      <childElements />
    </childElement>
    <childElement id="74f8fbe7-52d6-4894-bc1e-f9c979d3454d" type="Template Output" typeId="d421c322-7a51-4094-89fa-e5d8a0a97b27">
      <name>Intent.ModuleBuilder.TemplateRegistration.FilePerModel</name>
      <display>Intent.ModuleBuilder.TemplateRegistration.FilePerModel</display>
      <externalReference>Intent.ModuleBuilder</externalReference>
      <isAbstract>false</isAbstract>
      <genericTypes />
      <isMapped>false</isMapped>
      <parentFolderId>205e5666-404f-4b0c-89c5-41fd7d8a36e8</parentFolderId>
      <packageId>8d838a3c-f5ed-4c5e-bae9-b366a4869881</packageId>
      <packageName>Intent.Modules.NET</packageName>
      <stereotypes>
        <stereotype stereotypeDefinitionId="967ae6f6-cc06-4b67-a391-44ed1aac1959" name="Template Output Settings">
          <addedByDefault>true</addedByDefault>
          <definitionPackageName>Intent.VisualStudio.Projects</definitionPackageName>
          <definitionPackageId>a0636ab7-d3a1-430b-9609-11a18aa3cc7f</definitionPackageId>
          <properties>
            <property name="2ae1addc-b4dc-4cc8-94e1-56ef8a5420aa" display="Is Enabled" value="true" isActive="true" />
            <property name="2d8e6d2c-785c-4708-9104-bd3e9781a86a" display="Registration Filter" isActive="true" />
          </properties>
        </stereotype>
      </stereotypes>
      <metadata>
        <entry key="status" value="assigned" />
      </metadata>
      <childElements />
    </childElement>
    <childElement id="d8202a71-2d13-4f3b-8ae4-14522c824962" type="Template Output" typeId="d421c322-7a51-4094-89fa-e5d8a0a97b27">
      <name>Intent.ModuleBuilder.TemplateRegistration.SingleFileListModel</name>
      <display>Intent.ModuleBuilder.TemplateRegistration.SingleFileListModel</display>
      <externalReference>Intent.ModuleBuilder</externalReference>
      <isAbstract>false</isAbstract>
      <genericTypes />
      <isMapped>false</isMapped>
      <parentFolderId>205e5666-404f-4b0c-89c5-41fd7d8a36e8</parentFolderId>
      <packageId>8d838a3c-f5ed-4c5e-bae9-b366a4869881</packageId>
      <packageName>Intent.Modules.NET</packageName>
      <stereotypes>
        <stereotype stereotypeDefinitionId="967ae6f6-cc06-4b67-a391-44ed1aac1959" name="Template Output Settings">
          <addedByDefault>true</addedByDefault>
          <definitionPackageName>Intent.VisualStudio.Projects</definitionPackageName>
          <definitionPackageId>a0636ab7-d3a1-430b-9609-11a18aa3cc7f</definitionPackageId>
          <properties>
            <property name="2ae1addc-b4dc-4cc8-94e1-56ef8a5420aa" display="Is Enabled" value="true" isActive="true" />
            <property name="2d8e6d2c-785c-4708-9104-bd3e9781a86a" display="Registration Filter" isActive="true" />
          </properties>
        </stereotype>
      </stereotypes>
      <metadata>
        <entry key="status" value="assigned" />
      </metadata>
      <childElements />
    </childElement>
    <childElement id="6d98065e-3ea5-48d6-8e40-1cca42626767" type="Template Output" typeId="d421c322-7a51-4094-89fa-e5d8a0a97b27">
      <name>Intent.ModuleBuilder.TemplateRegistration.SingleFileNoModel</name>
      <display>Intent.ModuleBuilder.TemplateRegistration.SingleFileNoModel</display>
      <externalReference>Intent.ModuleBuilder</externalReference>
      <isAbstract>false</isAbstract>
      <genericTypes />
      <isMapped>false</isMapped>
      <parentFolderId>205e5666-404f-4b0c-89c5-41fd7d8a36e8</parentFolderId>
      <packageId>8d838a3c-f5ed-4c5e-bae9-b366a4869881</packageId>
      <packageName>Intent.Modules.NET</packageName>
      <stereotypes>
        <stereotype stereotypeDefinitionId="967ae6f6-cc06-4b67-a391-44ed1aac1959" name="Template Output Settings">
          <addedByDefault>true</addedByDefault>
          <definitionPackageName>Intent.VisualStudio.Projects</definitionPackageName>
          <definitionPackageId>a0636ab7-d3a1-430b-9609-11a18aa3cc7f</definitionPackageId>
          <properties>
            <property name="2ae1addc-b4dc-4cc8-94e1-56ef8a5420aa" display="Is Enabled" value="true" isActive="true" />
            <property name="2d8e6d2c-785c-4708-9104-bd3e9781a86a" display="Registration Filter" isActive="true" />
          </properties>
        </stereotype>
      </stereotypes>
      <metadata>
        <entry key="status" value="assigned" />
      </metadata>
      <childElements />
    </childElement>
    <childElement id="1d5fa8cc-ee0f-41af-b0f9-08c1b92234bb" type="Template Output" typeId="d421c322-7a51-4094-89fa-e5d8a0a97b27">
      <name>Intent.ModuleBuilder.Templates.FileTemplateStringInterpolation</name>
      <display>Intent.ModuleBuilder.Templates.FileTemplateStringInterpolation</display>
      <externalReference>Intent.ModuleBuilder</externalReference>
      <isAbstract>false</isAbstract>
      <genericTypes />
      <isMapped>false</isMapped>
      <parentFolderId>205e5666-404f-4b0c-89c5-41fd7d8a36e8</parentFolderId>
      <packageId>8d838a3c-f5ed-4c5e-bae9-b366a4869881</packageId>
      <packageName>Intent.Modules.NET</packageName>
      <stereotypes>
        <stereotype stereotypeDefinitionId="967ae6f6-cc06-4b67-a391-44ed1aac1959" name="Template Output Settings">
          <addedByDefault>true</addedByDefault>
          <definitionPackageName>Intent.VisualStudio.Projects</definitionPackageName>
          <definitionPackageId>a0636ab7-d3a1-430b-9609-11a18aa3cc7f</definitionPackageId>
          <properties>
            <property name="2ae1addc-b4dc-4cc8-94e1-56ef8a5420aa" display="Is Enabled" value="true" isActive="true" />
            <property name="2d8e6d2c-785c-4708-9104-bd3e9781a86a" display="Registration Filter" isActive="true" />
          </properties>
        </stereotype>
      </stereotypes>
      <metadata>
        <entry key="status" value="assigned" />
      </metadata>
      <childElements />
    </childElement>
    <childElement id="523f5003-c86a-4ccd-a7b1-b41cb86a4c65" type="Template Output" typeId="d421c322-7a51-4094-89fa-e5d8a0a97b27">
      <name>Intent.ModuleBuilder.Templates.FileTemplateT4</name>
      <display>Intent.ModuleBuilder.Templates.FileTemplateT4</display>
      <externalReference>Intent.ModuleBuilder</externalReference>
      <isAbstract>false</isAbstract>
      <genericTypes />
      <isMapped>false</isMapped>
      <parentFolderId>205e5666-404f-4b0c-89c5-41fd7d8a36e8</parentFolderId>
      <packageId>8d838a3c-f5ed-4c5e-bae9-b366a4869881</packageId>
      <packageName>Intent.Modules.NET</packageName>
      <stereotypes>
        <stereotype stereotypeDefinitionId="967ae6f6-cc06-4b67-a391-44ed1aac1959" name="Template Output Settings">
          <addedByDefault>true</addedByDefault>
          <definitionPackageName>Intent.VisualStudio.Projects</definitionPackageName>
          <definitionPackageId>a0636ab7-d3a1-430b-9609-11a18aa3cc7f</definitionPackageId>
          <properties>
            <property name="2ae1addc-b4dc-4cc8-94e1-56ef8a5420aa" display="Is Enabled" value="true" isActive="true" />
            <property name="2d8e6d2c-785c-4708-9104-bd3e9781a86a" display="Registration Filter" isActive="true" />
          </properties>
        </stereotype>
      </stereotypes>
      <metadata>
        <entry key="status" value="assigned" />
      </metadata>
      <childElements />
    </childElement>
    <childElement id="295aaafa-aec1-4c60-9012-63aa1dffb511" type="Template Output" typeId="d421c322-7a51-4094-89fa-e5d8a0a97b27">
      <name>Intent.ModuleBuilder.Templates.StaticContentTemplateRegistration</name>
      <display>Intent.ModuleBuilder.Templates.StaticContentTemplateRegistration</display>
      <externalReference>Intent.ModuleBuilder</externalReference>
      <isAbstract>false</isAbstract>
      <genericTypes />
      <isMapped>false</isMapped>
      <parentFolderId>205e5666-404f-4b0c-89c5-41fd7d8a36e8</parentFolderId>
      <packageId>8d838a3c-f5ed-4c5e-bae9-b366a4869881</packageId>
      <packageName>Intent.Modules.NET</packageName>
      <stereotypes>
        <stereotype stereotypeDefinitionId="967ae6f6-cc06-4b67-a391-44ed1aac1959" name="Template Output Settings">
          <addedByDefault>true</addedByDefault>
          <definitionPackageName>Intent.VisualStudio.Projects</definitionPackageName>
          <definitionPackageId>a0636ab7-d3a1-430b-9609-11a18aa3cc7f</definitionPackageId>
          <properties>
            <property name="2ae1addc-b4dc-4cc8-94e1-56ef8a5420aa" display="Is Enabled" value="true" isActive="true" />
            <property name="2d8e6d2c-785c-4708-9104-bd3e9781a86a" display="Registration Filter" isActive="true" />
          </properties>
        </stereotype>
      </stereotypes>
      <metadata>
        <entry key="status" value="assigned" />
      </metadata>
      <childElements />
    </childElement>
    <childElement id="e88a6fa2-03cb-4629-a9e4-e4b2fa6c6ee1" type="Template Output" typeId="d421c322-7a51-4094-89fa-e5d8a0a97b27">
      <name>Intent.ModuleBuilder.Templates.TemplateDecoratorContract</name>
      <display>Intent.ModuleBuilder.Templates.TemplateDecoratorContract</display>
      <externalReference>Intent.ModuleBuilder</externalReference>
      <isAbstract>false</isAbstract>
      <genericTypes />
      <isMapped>false</isMapped>
      <parentFolderId>205e5666-404f-4b0c-89c5-41fd7d8a36e8</parentFolderId>
      <packageId>8d838a3c-f5ed-4c5e-bae9-b366a4869881</packageId>
      <packageName>Intent.Modules.NET</packageName>
      <stereotypes>
        <stereotype stereotypeDefinitionId="967ae6f6-cc06-4b67-a391-44ed1aac1959" name="Template Output Settings">
          <addedByDefault>true</addedByDefault>
          <definitionPackageName>Intent.VisualStudio.Projects</definitionPackageName>
          <definitionPackageId>a0636ab7-d3a1-430b-9609-11a18aa3cc7f</definitionPackageId>
          <properties>
            <property name="2ae1addc-b4dc-4cc8-94e1-56ef8a5420aa" display="Is Enabled" value="true" isActive="true" />
            <property name="2d8e6d2c-785c-4708-9104-bd3e9781a86a" display="Registration Filter" isActive="true" />
          </properties>
        </stereotype>
      </stereotypes>
      <metadata>
        <entry key="status" value="assigned" />
      </metadata>
      <childElements />
    </childElement>
    <childElement id="71fd5e63-301d-4626-b3dd-b0238b5858f4" type="Template Output" typeId="d421c322-7a51-4094-89fa-e5d8a0a97b27">
      <name>Intent.ModuleBuilder.Templates.TemplateExtensions</name>
      <display>Intent.ModuleBuilder.Templates.TemplateExtensions</display>
      <externalReference>Intent.ModuleBuilder</externalReference>
      <isAbstract>false</isAbstract>
      <genericTypes />
      <isMapped>false</isMapped>
      <parentFolderId>205e5666-404f-4b0c-89c5-41fd7d8a36e8</parentFolderId>
      <packageId>8d838a3c-f5ed-4c5e-bae9-b366a4869881</packageId>
      <packageName>Intent.Modules.NET</packageName>
      <stereotypes>
        <stereotype stereotypeDefinitionId="967ae6f6-cc06-4b67-a391-44ed1aac1959" name="Template Output Settings">
          <addedByDefault>true</addedByDefault>
          <definitionPackageName>Intent.VisualStudio.Projects</definitionPackageName>
          <definitionPackageId>a0636ab7-d3a1-430b-9609-11a18aa3cc7f</definitionPackageId>
          <properties>
            <property name="2ae1addc-b4dc-4cc8-94e1-56ef8a5420aa" display="Is Enabled" value="true" isActive="true" />
            <property name="2d8e6d2c-785c-4708-9104-bd3e9781a86a" display="Registration Filter" isActive="true" />
          </properties>
        </stereotype>
      </stereotypes>
      <metadata>
        <entry key="status" value="assigned" />
      </metadata>
      <childElements />
    </childElement>
  </childElements>
</class>