<?xml version="1.0" encoding="utf-8"?>
<class id="3e41ef1d-c382-4923-bd5e-cc98ca98222f" type="Folder" typeId="3407a825-1331-4f3f-89a4-901903ed97ce">
  <name>Templates</name>
  <display>Templates</display>
  <isAbstract>false</isAbstract>
  <sort-children>by-type-then-by-name</sort-children>
  <genericTypes />
  <isMapped>false</isMapped>
  <parentFolderId>6755d512-de99-44b6-b3b8-29bc0878ee25</parentFolderId>
  <packageId>c58fa070-9bb2-490e-8472-d902b56bdc66</packageId>
  <packageName>Intent.Modules.NET</packageName>
  <stereotypes>
    <stereotype stereotypeDefinitionId="61132551-825d-4c6e-b9f1-0f95249d08d4" name="Folder Options">
      <addedByDefault>true</addedByDefault>
      <definitionPackageName>Intent.VisualStudio.Projects</definitionPackageName>
      <definitionPackageId>a0636ab7-d3a1-430b-9609-11a18aa3cc7f</definitionPackageId>
      <properties>
        <property name="4bfbefd0-d22e-4ca0-9723-92ae273feca4" display="Namespace Provider" value="true" isActive="true" />
      </properties>
    </stereotype>
  </stereotypes>
  <metadata />
  <childElements>
    <childElement id="5ddf083a-666f-498b-93fe-7ae11d2e5bed" type="Template Output" typeId="d421c322-7a51-4094-89fa-e5d8a0a97b27">
      <name>Intent.ModuleBuilder.CSharp.Templates.CSharpStringInterpolationTemplate</name>
      <display>Intent.ModuleBuilder.CSharp.Templates.CSharpStringInterpolationTemplate</display>
      <externalReference>Intent.ModuleBuilder.CSharp</externalReference>
      <isAbstract>false</isAbstract>
      <genericTypes />
      <isMapped>false</isMapped>
      <parentFolderId>3e41ef1d-c382-4923-bd5e-cc98ca98222f</parentFolderId>
      <packageId>c58fa070-9bb2-490e-8472-d902b56bdc66</packageId>
      <packageName>Intent.Modules.NET</packageName>
      <stereotypes />
      <metadata>
        <entry key="status" value="assigned" />
      </metadata>
      <childElements />
    </childElement>
    <childElement id="03465efe-c11d-463a-9432-38af5cd5dbf6" type="Template Output" typeId="d421c322-7a51-4094-89fa-e5d8a0a97b27">
      <name>Intent.ModuleBuilder.CSharp.Templates.CSharpT4Template</name>
      <display>Intent.ModuleBuilder.CSharp.Templates.CSharpT4Template</display>
      <externalReference>Intent.ModuleBuilder.CSharp</externalReference>
      <isAbstract>false</isAbstract>
      <genericTypes />
      <isMapped>false</isMapped>
      <parentFolderId>3e41ef1d-c382-4923-bd5e-cc98ca98222f</parentFolderId>
      <packageId>c58fa070-9bb2-490e-8472-d902b56bdc66</packageId>
      <packageName>Intent.Modules.NET</packageName>
      <stereotypes />
      <metadata>
        <entry key="status" value="assigned" />
      </metadata>
      <childElements />
    </childElement>
    <childElement id="23e34d08-16b0-4d55-91cd-f842ede1aefa" type="Template Output" typeId="d421c322-7a51-4094-89fa-e5d8a0a97b27">
      <name>Intent.ModuleBuilder.CSharp.Templates.CSharpTemplate.T4Template.PreProcessed</name>
      <display>Intent.ModuleBuilder.CSharp.Templates.CSharpTemplate.T4Template.PreProcessed</display>
      <externalReference>Intent.ModuleBuilder.CSharp</externalReference>
      <isAbstract>false</isAbstract>
      <genericTypes />
      <isMapped>false</isMapped>
      <parentFolderId>3e41ef1d-c382-4923-bd5e-cc98ca98222f</parentFolderId>
      <packageId>c58fa070-9bb2-490e-8472-d902b56bdc66</packageId>
      <packageName>Intent.Modules.NET</packageName>
      <stereotypes />
      <metadata>
        <entry key="status" value="assigned" />
      </metadata>
      <childElements />
    </childElement>
    <childElement id="ff9af378-884a-4ce8-bb47-a06d178fe785" type="Template Output" typeId="d421c322-7a51-4094-89fa-e5d8a0a97b27">
      <name>Intent.ModuleBuilder.CSharp.Templates.CSharpTemplatePartial</name>
      <display>Intent.ModuleBuilder.CSharp.Templates.CSharpTemplatePartial</display>
      <externalReference>Intent.ModuleBuilder.CSharp</externalReference>
      <isAbstract>false</isAbstract>
      <genericTypes />
      <isMapped>false</isMapped>
      <parentFolderId>3e41ef1d-c382-4923-bd5e-cc98ca98222f</parentFolderId>
      <packageId>c58fa070-9bb2-490e-8472-d902b56bdc66</packageId>
      <packageName>Intent.Modules.NET</packageName>
      <stereotypes />
      <metadata>
        <entry key="status" value="assigned" />
      </metadata>
      <childElements />
    </childElement>
    <childElement id="a99c99a7-4297-4757-887c-eadc4a646171" type="Template Output" typeId="d421c322-7a51-4094-89fa-e5d8a0a97b27">
      <name>Intent.ModuleBuilder.ProjectItemTemplate.Partial</name>
      <display>Intent.ModuleBuilder.ProjectItemTemplate.Partial</display>
      <externalReference>Intent.ModuleBuilder</externalReference>
      <isAbstract>false</isAbstract>
      <genericTypes />
      <isMapped>false</isMapped>
      <parentFolderId>3e41ef1d-c382-4923-bd5e-cc98ca98222f</parentFolderId>
      <packageId>c58fa070-9bb2-490e-8472-d902b56bdc66</packageId>
      <packageName>Intent.Modules.NET</packageName>
      <stereotypes />
      <metadata>
        <entry key="status" value="assigned" />
      </metadata>
      <childElements />
    </childElement>
    <childElement id="04fdabfb-c953-47ea-a486-84608afbcdee" type="Template Output" typeId="d421c322-7a51-4094-89fa-e5d8a0a97b27">
      <name>Intent.ModuleBuilder.ProjectItemTemplate.T4Template.PreProcessed</name>
      <display>Intent.ModuleBuilder.ProjectItemTemplate.T4Template.PreProcessed</display>
      <externalReference>Intent.ModuleBuilder</externalReference>
      <isAbstract>false</isAbstract>
      <genericTypes />
      <isMapped>false</isMapped>
      <parentFolderId>3e41ef1d-c382-4923-bd5e-cc98ca98222f</parentFolderId>
      <packageId>c58fa070-9bb2-490e-8472-d902b56bdc66</packageId>
      <packageName>Intent.Modules.NET</packageName>
      <stereotypes />
      <metadata>
        <entry key="status" value="assigned" />
      </metadata>
      <childElements />
    </childElement>
    <childElement id="b0e9495d-cc43-47b5-90fb-5f04a1edaf14" type="Template Output" typeId="d421c322-7a51-4094-89fa-e5d8a0a97b27">
      <name>Intent.ModuleBuilder.TemplateRegistration.Custom</name>
      <display>Intent.ModuleBuilder.TemplateRegistration.Custom</display>
      <externalReference>Intent.ModuleBuilder</externalReference>
      <isAbstract>false</isAbstract>
      <genericTypes />
      <isMapped>false</isMapped>
      <parentFolderId>3e41ef1d-c382-4923-bd5e-cc98ca98222f</parentFolderId>
      <packageId>c58fa070-9bb2-490e-8472-d902b56bdc66</packageId>
      <packageName>Intent.Modules.NET</packageName>
      <stereotypes />
      <metadata>
        <entry key="status" value="assigned" />
      </metadata>
      <childElements />
    </childElement>
    <childElement id="b0220f9f-5dac-428f-b8a4-1f6b7fb68ea8" type="Template Output" typeId="d421c322-7a51-4094-89fa-e5d8a0a97b27">
      <name>Intent.ModuleBuilder.TemplateRegistration.FilePerModel</name>
      <display>Intent.ModuleBuilder.TemplateRegistration.FilePerModel</display>
      <externalReference>Intent.ModuleBuilder</externalReference>
      <isAbstract>false</isAbstract>
      <genericTypes />
      <isMapped>false</isMapped>
      <parentFolderId>3e41ef1d-c382-4923-bd5e-cc98ca98222f</parentFolderId>
      <packageId>c58fa070-9bb2-490e-8472-d902b56bdc66</packageId>
      <packageName>Intent.Modules.NET</packageName>
      <stereotypes />
      <metadata>
        <entry key="status" value="assigned" />
      </metadata>
      <childElements />
    </childElement>
    <childElement id="ccdf9716-a791-44c1-88c7-560912034a28" type="Template Output" typeId="d421c322-7a51-4094-89fa-e5d8a0a97b27">
      <name>Intent.ModuleBuilder.TemplateRegistration.SingleFileListModel</name>
      <display>Intent.ModuleBuilder.TemplateRegistration.SingleFileListModel</display>
      <externalReference>Intent.ModuleBuilder</externalReference>
      <isAbstract>false</isAbstract>
      <genericTypes />
      <isMapped>false</isMapped>
      <parentFolderId>3e41ef1d-c382-4923-bd5e-cc98ca98222f</parentFolderId>
      <packageId>c58fa070-9bb2-490e-8472-d902b56bdc66</packageId>
      <packageName>Intent.Modules.NET</packageName>
      <stereotypes />
      <metadata>
        <entry key="status" value="assigned" />
      </metadata>
      <childElements />
    </childElement>
    <childElement id="a4faade2-7337-486d-96e4-275099955ab8" type="Template Output" typeId="d421c322-7a51-4094-89fa-e5d8a0a97b27">
      <name>Intent.ModuleBuilder.TemplateRegistration.SingleFileNoModel</name>
      <display>Intent.ModuleBuilder.TemplateRegistration.SingleFileNoModel</display>
      <externalReference>Intent.ModuleBuilder</externalReference>
      <isAbstract>false</isAbstract>
      <genericTypes />
      <isMapped>false</isMapped>
      <parentFolderId>3e41ef1d-c382-4923-bd5e-cc98ca98222f</parentFolderId>
      <packageId>c58fa070-9bb2-490e-8472-d902b56bdc66</packageId>
      <packageName>Intent.Modules.NET</packageName>
      <stereotypes />
      <metadata>
        <entry key="status" value="assigned" />
      </metadata>
      <childElements />
    </childElement>
    <childElement id="b1b52c9e-d8c0-4cac-ae2b-ccc86969fe11" type="Template Output" typeId="d421c322-7a51-4094-89fa-e5d8a0a97b27">
      <name>Intent.ModuleBuilder.Templates.FileTemplateStringInterpolation</name>
      <display>Intent.ModuleBuilder.Templates.FileTemplateStringInterpolation</display>
      <externalReference>Intent.ModuleBuilder</externalReference>
      <isAbstract>false</isAbstract>
      <genericTypes />
      <isMapped>false</isMapped>
      <parentFolderId>3e41ef1d-c382-4923-bd5e-cc98ca98222f</parentFolderId>
      <packageId>c58fa070-9bb2-490e-8472-d902b56bdc66</packageId>
      <packageName>Intent.Modules.NET</packageName>
      <stereotypes />
      <metadata>
        <entry key="status" value="assigned" />
      </metadata>
      <childElements />
    </childElement>
    <childElement id="956ec427-00f0-4379-9bef-3f11548540ce" type="Template Output" typeId="d421c322-7a51-4094-89fa-e5d8a0a97b27">
      <name>Intent.ModuleBuilder.Templates.FileTemplateT4</name>
      <display>Intent.ModuleBuilder.Templates.FileTemplateT4</display>
      <externalReference>Intent.ModuleBuilder</externalReference>
      <isAbstract>false</isAbstract>
      <genericTypes />
      <isMapped>false</isMapped>
      <parentFolderId>3e41ef1d-c382-4923-bd5e-cc98ca98222f</parentFolderId>
      <packageId>c58fa070-9bb2-490e-8472-d902b56bdc66</packageId>
      <packageName>Intent.Modules.NET</packageName>
      <stereotypes />
      <metadata>
        <entry key="status" value="assigned" />
      </metadata>
      <childElements />
    </childElement>
    <childElement id="de911152-382d-45ca-8af0-5ed7b77c9b6f" type="Template Output" typeId="d421c322-7a51-4094-89fa-e5d8a0a97b27">
      <name>Intent.ModuleBuilder.Templates.StaticContentTemplateRegistration</name>
      <display>Intent.ModuleBuilder.Templates.StaticContentTemplateRegistration</display>
      <externalReference>Intent.ModuleBuilder</externalReference>
      <isAbstract>false</isAbstract>
      <genericTypes />
      <isMapped>false</isMapped>
      <parentFolderId>3e41ef1d-c382-4923-bd5e-cc98ca98222f</parentFolderId>
      <packageId>c58fa070-9bb2-490e-8472-d902b56bdc66</packageId>
      <packageName>Intent.Modules.NET</packageName>
      <stereotypes />
      <metadata>
        <entry key="status" value="assigned" />
      </metadata>
      <childElements />
    </childElement>
    <childElement id="f790fe5c-ad32-45f1-9a00-9e3621d2cdf1" type="Template Output" typeId="d421c322-7a51-4094-89fa-e5d8a0a97b27">
      <name>Intent.ModuleBuilder.Templates.TemplateDecoratorContract</name>
      <display>Intent.ModuleBuilder.Templates.TemplateDecoratorContract</display>
      <externalReference>Intent.ModuleBuilder</externalReference>
      <isAbstract>false</isAbstract>
      <genericTypes />
      <isMapped>false</isMapped>
      <parentFolderId>3e41ef1d-c382-4923-bd5e-cc98ca98222f</parentFolderId>
      <packageId>c58fa070-9bb2-490e-8472-d902b56bdc66</packageId>
      <packageName>Intent.Modules.NET</packageName>
      <stereotypes />
      <metadata>
        <entry key="status" value="assigned" />
      </metadata>
      <childElements />
    </childElement>
    <childElement id="4346a538-e038-41d5-92b2-7a6e6bc036f7" type="Template Output" typeId="d421c322-7a51-4094-89fa-e5d8a0a97b27">
      <name>Intent.ModuleBuilder.Templates.TemplateExtensions</name>
      <display>Intent.ModuleBuilder.Templates.TemplateExtensions</display>
      <externalReference>Intent.ModuleBuilder</externalReference>
      <isAbstract>false</isAbstract>
      <genericTypes />
      <isMapped>false</isMapped>
      <parentFolderId>3e41ef1d-c382-4923-bd5e-cc98ca98222f</parentFolderId>
      <packageId>c58fa070-9bb2-490e-8472-d902b56bdc66</packageId>
      <packageName>Intent.Modules.NET</packageName>
      <stereotypes />
      <metadata>
        <entry key="status" value="assigned" />
      </metadata>
      <childElements />
    </childElement>
  </childElements>
</class>