<?xml version="1.0" encoding="utf-8"?>
<class id="48c2e2fc-38e5-4997-a72d-362d3f7a0b43" type="Template Decorator" typeId="f0f46278-29ea-42bd-9206-0e7034f623bc">
  <name>OutboxTableSpecification</name>
  <display>OutboxTableSpecification: DbContextDecoratorBase</display>
  <isAbstract>false</isAbstract>
  <genericTypes />
  <typeReference id="fe813cee-edfa-47c4-8e4c-1c63e8383e7b">
    <typeId>c35164c7-3797-476e-89ba-c98b96de3176</typeId>
    <isNavigable>true</isNavigable>
    <isNullable>false</isNullable>
    <isCollection>false</isCollection>
    <isRequired>true</isRequired>
    <typePackageName>Intent.EntityFrameworkCore</typePackageName>
    <typePackageId>a9d2a398-04e4-4300-9fbb-768568c65f9e</typePackageId>
    <stereotypes />
    <genericTypeParameters />
  </typeReference>
  <isMapped>false</isMapped>
  <parentFolderId>d728759c-4d35-4a38-9b96-e5e104539948</parentFolderId>
  <packageId>d728759c-4d35-4a38-9b96-e5e104539948</packageId>
  <packageName>Intent.Eventing.MassTransit.OutboxPersistence</packageName>
  <stereotypes />
  <metadata />
  <childElements />
</class>