<?xml version="1.0" encoding="utf-8"?>
<class id="84298280-29cc-4d20-80e7-33b169128436" type="Association Extension" typeId="41cb9c1a-063e-4ff4-889a-7501235351eb">
  <name>Association Extension</name>
  <display>Association Extension: Association</display>
  <isAbstract>false</isAbstract>
  <sort-children>by-type-then-manually</sort-children>
  <genericTypes />
  <typeReference id="124496c3-7c0b-41d2-808a-cd0205c4155d">
    <typeId>eaf9ed4e-0b61-4ac1-ba88-09f912c12087</typeId>
    <isNavigable>true</isNavigable>
    <isNullable>false</isNullable>
    <isCollection>false</isCollection>
    <isRequired>true</isRequired>
    <typePackageName>Intent.Modelers.Domain</typePackageName>
    <typePackageId>6572b98d-5e13-4d4b-9ffc-820057da974e</typePackageId>
    <stereotypes />
    <genericTypeParameters />
  </typeReference>
  <isMapped>false</isMapped>
  <parentFolderId>232b1576-74b7-45e1-bc24-2ddc42529d5d</parentFolderId>
  <packageId>3f385f6e-90c2-4071-bde2-7d8943252fd5</packageId>
  <packageName>Intent.MongoDb</packageName>
  <stereotypes />
  <metadata />
  <childElements>
    <childElement id="3c684c08-1051-4ea0-aec9-f1b91f9efc3a" type="Association Source End Extension" typeId="66ec1dcd-a0c3-45ac-ad62-f2d9d7064bb3">
      <name>[source]</name>
      <display>[source end extension]</display>
      <isAbstract>false</isAbstract>
      <genericTypes />
      <isMapped>false</isMapped>
      <parentFolderId>84298280-29cc-4d20-80e7-33b169128436</parentFolderId>
      <packageId>3f385f6e-90c2-4071-bde2-7d8943252fd5</packageId>
      <packageName>Intent.MongoDb</packageName>
      <stereotypes>
        <stereotype stereotypeDefinitionId="1cd7ee9e-614e-4770-a831-d6cdaa56027c" name="Association End Extension Settings">
          <addedByDefault>true</addedByDefault>
          <definitionPackageName>Intent.ModuleBuilder</definitionPackageName>
          <definitionPackageId>9972b2a9-b749-4bba-b5c8-824bf694c6ef</definitionPackageId>
          <properties>
            <property name="e7d1e8c5-6748-4f56-8a92-4f413b598412" display="Display Name" isActive="true" />
            <property name="f957891b-3aef-48b2-9241-71c8a45a8fbb" display="Hint" isActive="true" />
            <property name="05d63939-2d01-4b12-8bcf-d6751c7c32b8" display="Target Types" isActive="true" />
            <property name="ced53770-7796-42de-850e-5cd523e368f9" display="Default Type Id" isActive="true" />
            <property name="585f6851-b6a5-4d39-9804-256cefcb10ab" display="Allow Navigable" value="Inherit" isActive="true" />
            <property name="c5da195d-90af-4d23-9a62-6aca60a9b304" display="Allow Nullable" value="Inherit" isActive="true" />
            <property name="558c27e8-dc8b-40ae-8633-fd42f0077268" display="Allow Collection" value="Inherit" isActive="true" />
          </properties>
        </stereotype>
      </stereotypes>
      <metadata />
      <childElements />
    </childElement>
    <childElement id="4a238edc-8ae3-4b2f-8f78-1c1704a01dd0" type="Association Target End Extension" typeId="1cc6c731-af5f-41a0-9e82-44486f45b903">
      <name>[destination]</name>
      <display>[target end extension]</display>
      <isAbstract>false</isAbstract>
      <genericTypes />
      <isMapped>false</isMapped>
      <parentFolderId>84298280-29cc-4d20-80e7-33b169128436</parentFolderId>
      <packageId>3f385f6e-90c2-4071-bde2-7d8943252fd5</packageId>
      <packageName>Intent.MongoDb</packageName>
      <stereotypes>
        <stereotype stereotypeDefinitionId="1cd7ee9e-614e-4770-a831-d6cdaa56027c" name="Association End Extension Settings">
          <addedByDefault>true</addedByDefault>
          <definitionPackageName>Intent.ModuleBuilder</definitionPackageName>
          <definitionPackageId>9972b2a9-b749-4bba-b5c8-824bf694c6ef</definitionPackageId>
          <properties>
            <property name="e7d1e8c5-6748-4f56-8a92-4f413b598412" display="Display Name" isActive="true" />
            <property name="f957891b-3aef-48b2-9241-71c8a45a8fbb" display="Hint" isActive="true" />
            <property name="05d63939-2d01-4b12-8bcf-d6751c7c32b8" display="Target Types" isActive="true" />
            <property name="ced53770-7796-42de-850e-5cd523e368f9" display="Default Type Id" isActive="true" />
            <property name="585f6851-b6a5-4d39-9804-256cefcb10ab" display="Allow Navigable" value="Inherit" isActive="true" />
            <property name="c5da195d-90af-4d23-9a62-6aca60a9b304" display="Allow Nullable" value="Inherit" isActive="true" />
            <property name="558c27e8-dc8b-40ae-8633-fd42f0077268" display="Allow Collection" value="Inherit" isActive="true" />
          </properties>
        </stereotype>
      </stereotypes>
      <metadata />
      <childElements />
    </childElement>
    <childElement id="804d9a71-fb3c-42a1-a574-6dce9d8c06bd" type="Association Event Settings" typeId="1bdee938-8569-4fbf-84b4-8522d2cbee32">
      <name>[events]</name>
      <display>[events]</display>
      <isAbstract>false</isAbstract>
      <sort-children>by-type-then-by-name</sort-children>
      <genericTypes />
      <isMapped>false</isMapped>
      <parentFolderId>84298280-29cc-4d20-80e7-33b169128436</parentFolderId>
      <packageId>3f385f6e-90c2-4071-bde2-7d8943252fd5</packageId>
      <packageName>Intent.MongoDb</packageName>
      <stereotypes />
      <metadata />
      <childElements>
        <childElement id="531e060c-43f4-4166-a537-22d208c21918" type="Association Event Handler" typeId="f9b3e6fd-3c51-4ed9-b214-cb7f5fc1cf7c">
          <name>On Changed</name>
          <display>On Changed: Script</display>
          <isAbstract>false</isAbstract>
          <genericTypes />
          <typeReference id="e7257f4e-0fd4-4f8c-b467-648743ecc4f5">
            <typeId>043eee26-1591-42ac-9f2c-fc911b070eb1</typeId>
            <isNavigable>true</isNavigable>
            <isNullable>false</isNullable>
            <isCollection>false</isCollection>
            <isRequired>true</isRequired>
            <typePackageName>Intent.ModuleBuilder</typePackageName>
            <typePackageId>9972b2a9-b749-4bba-b5c8-824bf694c6ef</typePackageId>
            <stereotypes />
            <genericTypeParameters />
          </typeReference>
          <isMapped>false</isMapped>
          <parentFolderId>804d9a71-fb3c-42a1-a574-6dce9d8c06bd</parentFolderId>
          <packageId>3f385f6e-90c2-4071-bde2-7d8943252fd5</packageId>
          <packageName>Intent.MongoDb</packageName>
          <stereotypes>
            <stereotype stereotypeDefinitionId="1f88f1ac-b96a-4ae7-9047-883c2fa3b3df" name="Script Settings">
              <addedByDefault>true</addedByDefault>
              <definitionPackageName>Intent.ModuleBuilder</definitionPackageName>
              <definitionPackageId>9972b2a9-b749-4bba-b5c8-824bf694c6ef</definitionPackageId>
              <properties>
                <property name="d418d372-ae82-4852-81b1-20b78a26eb6c" display="Script" value="let targetClass = association.typeReference.getType();&#xD;&#xA;const GuidTypeId = &quot;6b649125-18ea-48fd-a6ba-0bfff0d8f488&quot;;&#xD;&#xA;if (!isAggregateRoot(targetClass)) {&#xD;&#xA;    targetClass.getChildren(&quot;Attribute&quot;).filter(x =&gt; x.hasMetadata(&quot;id&quot;)).forEach(x =&gt; x.typeReference.setType(GuidTypeId));&#xD;&#xA;}&#xD;&#xA;function isAggregateRoot(element) {&#xD;&#xA;    return !element.getAssociations(&quot;Association&quot;)&#xD;&#xA;        .some(x =&gt; x.isSourceEnd() &amp;&amp; !x.typeReference.isCollection &amp;&amp; !x.typeReference.isNullable);&#xD;&#xA;}" isActive="true" />
              </properties>
            </stereotype>
          </stereotypes>
          <metadata />
          <childElements />
        </childElement>
        <childElement id="3e9d945d-8e57-4602-b6c5-28f1a854aa7d" type="Association Event Handler" typeId="f9b3e6fd-3c51-4ed9-b214-cb7f5fc1cf7c">
          <name>On Created</name>
          <display>On Created: Script</display>
          <isAbstract>false</isAbstract>
          <genericTypes />
          <typeReference id="306b19a2-6e23-463b-a1ac-6f25619f3503">
            <typeId>043eee26-1591-42ac-9f2c-fc911b070eb1</typeId>
            <isNavigable>true</isNavigable>
            <isNullable>false</isNullable>
            <isCollection>false</isCollection>
            <isRequired>true</isRequired>
            <typePackageName>Intent.ModuleBuilder</typePackageName>
            <typePackageId>9972b2a9-b749-4bba-b5c8-824bf694c6ef</typePackageId>
            <stereotypes />
            <genericTypeParameters />
          </typeReference>
          <isMapped>false</isMapped>
          <parentFolderId>804d9a71-fb3c-42a1-a574-6dce9d8c06bd</parentFolderId>
          <packageId>3f385f6e-90c2-4071-bde2-7d8943252fd5</packageId>
          <packageName>Intent.MongoDb</packageName>
          <stereotypes>
            <stereotype stereotypeDefinitionId="1f88f1ac-b96a-4ae7-9047-883c2fa3b3df" name="Script Settings">
              <addedByDefault>true</addedByDefault>
              <definitionPackageName>Intent.ModuleBuilder</definitionPackageName>
              <definitionPackageId>9972b2a9-b749-4bba-b5c8-824bf694c6ef</definitionPackageId>
              <properties>
                <property name="d418d372-ae82-4852-81b1-20b78a26eb6c" display="Script" value="if (!association) {&#xD;&#xA;    return;&#xD;&#xA;}&#xD;&#xA;let sourceEnd = association.getOtherEnd().typeReference;&#xD;&#xA;if (sourceEnd.getType().getPackage().specialization !== &quot;Mongo Domain Package&quot;) {&#xD;&#xA;    return;&#xD;&#xA;}&#xD;&#xA;//let targetEnd = association.typeReference;&#xD;&#xA;sourceEnd.setIsCollection(false);&#xD;&#xA;sourceEnd.setIsNullable(false);&#xD;&#xA;//targetEnd.setIsCollection(false);&#xD;&#xA;//targetEnd.setIsNullable(false);" isActive="true" />
              </properties>
            </stereotype>
          </stereotypes>
          <metadata />
          <childElements />
        </childElement>
        <childElement id="ee5261e2-cc35-4058-a2e6-6319c71175ae" type="Association Event Handler" typeId="f9b3e6fd-3c51-4ed9-b214-cb7f5fc1cf7c">
          <name>On Deleted</name>
          <display>On Deleted: Script</display>
          <isAbstract>false</isAbstract>
          <genericTypes />
          <typeReference id="3b49d9c9-4dae-4287-9ef8-2b783c8ddd47">
            <typeId>043eee26-1591-42ac-9f2c-fc911b070eb1</typeId>
            <isNavigable>true</isNavigable>
            <isNullable>false</isNullable>
            <isCollection>false</isCollection>
            <isRequired>true</isRequired>
            <typePackageName>Intent.ModuleBuilder</typePackageName>
            <typePackageId>9972b2a9-b749-4bba-b5c8-824bf694c6ef</typePackageId>
            <stereotypes />
            <genericTypeParameters />
          </typeReference>
          <isMapped>false</isMapped>
          <parentFolderId>804d9a71-fb3c-42a1-a574-6dce9d8c06bd</parentFolderId>
          <packageId>3f385f6e-90c2-4071-bde2-7d8943252fd5</packageId>
          <packageName>Intent.MongoDb</packageName>
          <stereotypes>
            <stereotype stereotypeDefinitionId="1f88f1ac-b96a-4ae7-9047-883c2fa3b3df" name="Script Settings">
              <addedByDefault>true</addedByDefault>
              <definitionPackageName>Intent.ModuleBuilder</definitionPackageName>
              <definitionPackageId>9972b2a9-b749-4bba-b5c8-824bf694c6ef</definitionPackageId>
              <properties>
                <property name="d418d372-ae82-4852-81b1-20b78a26eb6c" display="Script" value="let targetClass = association.typeReference.getType();&#xD;&#xA;if (isAggregateRoot(targetClass)) {&#xD;&#xA;    targetClass.getChildren(&quot;Attribute&quot;).filter(x =&gt; x.hasMetadata(&quot;id&quot;)).forEach(x =&gt; x.typeReference.setType(getDefaultIdType()));&#xD;&#xA;}&#xD;&#xA;function isAggregateRoot(element) {&#xD;&#xA;    return !element.getAssociations(&quot;Association&quot;)&#xD;&#xA;        .some(x =&gt; x.isSourceEnd() &amp;&amp; !x.typeReference.isCollection &amp;&amp; !x.typeReference.isNullable);&#xD;&#xA;}&#xD;&#xA;function getDefaultIdType() {&#xD;&#xA;    const StringTypeId = &quot;d384db9c-a279-45e1-801e-e4e8099625f2&quot;;&#xD;&#xA;    const GuidTypeId = &quot;6b649125-18ea-48fd-a6ba-0bfff0d8f488&quot;;&#xD;&#xA;    const IntTypeId = &quot;fb0a362d-e9e2-40de-b6ff-5ce8167cbe74&quot;;&#xD;&#xA;    const LongTypeId = &quot;33013006-E404-48C2-AC46-24EF5A5774FD&quot;;&#xD;&#xA;    const MongoSettingId = &quot;d5581fe8-7385-4bb6-88dc-8940e20ec1d4&quot;;&#xD;&#xA;    switch (application.getSettings(MongoSettingId)?.getField(&quot;Id Type&quot;)?.value) {&#xD;&#xA;        default:&#xD;&#xA;            return StringTypeId;&#xD;&#xA;        case &quot;guid&quot;:&#xD;&#xA;            return GuidTypeId;&#xD;&#xA;        case &quot;int&quot;:&#xD;&#xA;            return IntTypeId;&#xD;&#xA;        case &quot;long&quot;:&#xD;&#xA;            return LongTypeId;&#xD;&#xA;    }&#xD;&#xA;}" isActive="true" />
              </properties>
            </stereotype>
          </stereotypes>
          <metadata />
          <childElements />
        </childElement>
      </childElements>
    </childElement>
  </childElements>
</class>