<?xml version="1.0" encoding="utf-8"?>
<class id="46db1846-1f8c-46e3-9fd2-b0aa080432ed" type="NuGet Package" typeId="f747cc37-29ee-488a-8dbe-755e856a842d">
  <name>Microsoft.Extensions.Configuration.Json</name>
  <display>Microsoft.Extensions.Configuration.Json</display>
  <isAbstract>false</isAbstract>
  <sort-children>by-type-then-by-name</sort-children>
  <genericTypes />
  <isMapped>false</isMapped>
  <parentFolderId>9c64d408-5bbd-4c1d-a9ab-2259f87b53e5</parentFolderId>
  <packageId>5d8b794d-4032-489f-ac2b-8a73a23a6bf3</packageId>
  <packageName>Intent.EntityFrameworkCore.DesignTimeDbContextFactory</packageName>
  <stereotypes>
    <stereotype stereotypeDefinitionId="265221a5-779c-46c9-a367-8b07b435803b" name="Package Settings">
      <addedByDefault>false</addedByDefault>
      <definitionPackageName>Intent.ModuleBuilder.CSharp</definitionPackageName>
      <definitionPackageId>f2bfb0f7-d304-466f-b923-021d4016b48d</definitionPackageId>
      <properties>
        <property name="4de9cc21-d4fb-4d52-8dfd-2eb6cf267a9a" display="Friendly Name" isActive="true" />
        <property name="67c7c4d8-40ed-48f9-a83c-985eedb32141" display="Locked" value="false" isActive="true" />
        <property name="c166c7cf-45e3-484b-9ec5-f7300951f897" display="Private Assets" isActive="true" />
        <property name="6bd6430c-8011-435e-bb73-6013477a875d" display="Include Assets" isActive="true" />
      </properties>
    </stereotype>
  </stereotypes>
  <metadata />
  <childElements>
    <childElement id="cc642467-d26e-4038-9ffe-3443322487e2" type="Package Version" typeId="231f8cf8-517b-4801-9682-991d22f4e662">
      <name>9.0.6</name>
      <display>9.0.5 ( &gt;= .NETCoreApp,Version=v8.0 )</display>
      <isAbstract>false</isAbstract>
      <sort-children>by-type-then-by-name</sort-children>
      <genericTypes />
      <isMapped>false</isMapped>
      <parentFolderId>46db1846-1f8c-46e3-9fd2-b0aa080432ed</parentFolderId>
      <packageId>5d8b794d-4032-489f-ac2b-8a73a23a6bf3</packageId>
      <packageName>Intent.EntityFrameworkCore.DesignTimeDbContextFactory</packageName>
      <stereotypes>
        <stereotype stereotypeDefinitionId="7af88c37-ce54-49fc-b577-bde869c23462" name="Package Version Settings">
          <addedByDefault>true</addedByDefault>
          <definitionPackageName>Intent.ModuleBuilder.CSharp</definitionPackageName>
          <definitionPackageId>f2bfb0f7-d304-466f-b923-021d4016b48d</definitionPackageId>
          <properties>
            <property name="b01cea92-0ca1-4dbe-acab-d0f52b39e003" display="Minimum Target Framework" value=".NETCoreApp,Version=v8.0" isActive="true" />
            <property name="d00692b1-6d17-4f1e-9386-a1d0d3ab7b57" display="Locked" value="false" isActive="true" />
          </properties>
        </stereotype>
      </stereotypes>
      <metadata />
      <childElements>
        <childElement id="2c53ba8c-44b8-4efc-a6e1-b7e84ea8f440" type="NuGet Dependency" typeId="3097322a-a058-4058-beed-4fcd6272f61d">
          <name>Microsoft.Extensions.Configuration.Abstractions</name>
          <isAbstract>false</isAbstract>
          <value>9.0.6</value>
          <genericTypes />
          <isMapped>false</isMapped>
          <parentFolderId>cc642467-d26e-4038-9ffe-3443322487e2</parentFolderId>
          <stereotypes />
          <metadata />
          <childElements />
        </childElement>
        <childElement id="8d6ab44d-7f17-4f46-8887-7f0a12eaaacd" type="NuGet Dependency" typeId="3097322a-a058-4058-beed-4fcd6272f61d">
          <name>Microsoft.Extensions.Configuration.FileExtensions</name>
          <isAbstract>false</isAbstract>
          <value>9.0.6</value>
          <genericTypes />
          <isMapped>false</isMapped>
          <parentFolderId>cc642467-d26e-4038-9ffe-3443322487e2</parentFolderId>
          <stereotypes />
          <metadata />
          <childElements />
        </childElement>
        <childElement id="a92edead-b401-4046-8e02-bce807a74c99" type="NuGet Dependency" typeId="3097322a-a058-4058-beed-4fcd6272f61d">
          <name>Microsoft.Extensions.Configuration</name>
          <isAbstract>false</isAbstract>
          <value>9.0.6</value>
          <genericTypes />
          <isMapped>false</isMapped>
          <parentFolderId>cc642467-d26e-4038-9ffe-3443322487e2</parentFolderId>
          <stereotypes />
          <metadata />
          <childElements />
        </childElement>
        <childElement id="54a04b6b-57f2-4148-8662-7b2c9680597b" type="NuGet Dependency" typeId="3097322a-a058-4058-beed-4fcd6272f61d">
          <name>Microsoft.Extensions.FileProviders.Abstractions</name>
          <isAbstract>false</isAbstract>
          <value>9.0.6</value>
          <genericTypes />
          <isMapped>false</isMapped>
          <parentFolderId>cc642467-d26e-4038-9ffe-3443322487e2</parentFolderId>
          <stereotypes />
          <metadata />
          <childElements />
        </childElement>
        <childElement id="97d0e7de-b747-4345-95fd-c992805d798e" type="NuGet Dependency" typeId="3097322a-a058-4058-beed-4fcd6272f61d">
          <name>System.Text.Json</name>
          <isAbstract>false</isAbstract>
          <value>9.0.6</value>
          <genericTypes />
          <isMapped>false</isMapped>
          <parentFolderId>cc642467-d26e-4038-9ffe-3443322487e2</parentFolderId>
          <stereotypes />
          <metadata />
          <childElements />
        </childElement>
      </childElements>
    </childElement>
    <childElement id="291c92d0-d0cf-4d12-85f2-8d52e4d3330b" type="Package Version" typeId="231f8cf8-517b-4801-9682-991d22f4e662">
      <name>9.0.6</name>
      <display>9.0.5 ( &gt;= .NETStandard,Version=v2.0 )</display>
      <isAbstract>false</isAbstract>
      <sort-children>by-type-then-by-name</sort-children>
      <genericTypes />
      <isMapped>false</isMapped>
      <parentFolderId>46db1846-1f8c-46e3-9fd2-b0aa080432ed</parentFolderId>
      <packageId>5d8b794d-4032-489f-ac2b-8a73a23a6bf3</packageId>
      <packageName>Intent.EntityFrameworkCore.DesignTimeDbContextFactory</packageName>
      <stereotypes>
        <stereotype stereotypeDefinitionId="7af88c37-ce54-49fc-b577-bde869c23462" name="Package Version Settings">
          <addedByDefault>false</addedByDefault>
          <definitionPackageName>Intent.ModuleBuilder.CSharp</definitionPackageName>
          <definitionPackageId>f2bfb0f7-d304-466f-b923-021d4016b48d</definitionPackageId>
          <properties>
            <property name="b01cea92-0ca1-4dbe-acab-d0f52b39e003" display="Minimum Target Framework" value=".NETStandard,Version=v2.0" isActive="true" />
            <property name="d00692b1-6d17-4f1e-9386-a1d0d3ab7b57" display="Locked" value="false" isActive="true" />
          </properties>
        </stereotype>
      </stereotypes>
      <metadata />
      <childElements>
        <childElement id="b47f84c1-9cb4-4996-94fe-bc7fd5b579ee" type="NuGet Dependency" typeId="3097322a-a058-4058-beed-4fcd6272f61d">
          <name>Microsoft.Extensions.Configuration.Abstractions</name>
          <isAbstract>false</isAbstract>
          <value>9.0.6</value>
          <genericTypes />
          <isMapped>false</isMapped>
          <parentFolderId>291c92d0-d0cf-4d12-85f2-8d52e4d3330b</parentFolderId>
          <stereotypes />
          <metadata />
          <childElements />
        </childElement>
        <childElement id="2ccf3701-85a2-423e-9dec-c4cf7a2f47ea" type="NuGet Dependency" typeId="3097322a-a058-4058-beed-4fcd6272f61d">
          <name>Microsoft.Extensions.Configuration.FileExtensions</name>
          <isAbstract>false</isAbstract>
          <value>9.0.6</value>
          <genericTypes />
          <isMapped>false</isMapped>
          <parentFolderId>291c92d0-d0cf-4d12-85f2-8d52e4d3330b</parentFolderId>
          <stereotypes />
          <metadata />
          <childElements />
        </childElement>
        <childElement id="901571a9-6f5b-441e-9d0b-34413084f458" type="NuGet Dependency" typeId="3097322a-a058-4058-beed-4fcd6272f61d">
          <name>Microsoft.Extensions.Configuration</name>
          <isAbstract>false</isAbstract>
          <value>9.0.6</value>
          <genericTypes />
          <isMapped>false</isMapped>
          <parentFolderId>291c92d0-d0cf-4d12-85f2-8d52e4d3330b</parentFolderId>
          <stereotypes />
          <metadata />
          <childElements />
        </childElement>
        <childElement id="fee71192-4c6a-40f0-902d-5a33fa607a70" type="NuGet Dependency" typeId="3097322a-a058-4058-beed-4fcd6272f61d">
          <name>Microsoft.Extensions.FileProviders.Abstractions</name>
          <isAbstract>false</isAbstract>
          <value>9.0.6</value>
          <genericTypes />
          <isMapped>false</isMapped>
          <parentFolderId>291c92d0-d0cf-4d12-85f2-8d52e4d3330b</parentFolderId>
          <stereotypes />
          <metadata />
          <childElements />
        </childElement>
        <childElement id="eb200566-ba1f-4ec5-8ef0-ee1846627451" type="NuGet Dependency" typeId="3097322a-a058-4058-beed-4fcd6272f61d">
          <name>System.Text.Json</name>
          <isAbstract>false</isAbstract>
          <value>9.0.6</value>
          <genericTypes />
          <isMapped>false</isMapped>
          <parentFolderId>291c92d0-d0cf-4d12-85f2-8d52e4d3330b</parentFolderId>
          <stereotypes />
          <metadata />
          <childElements />
        </childElement>
      </childElements>
    </childElement>
    <childElement id="8e8418b0-e9a5-4113-80e9-931c19d72109" type="Package Version" typeId="231f8cf8-517b-4801-9682-991d22f4e662">
      <name>9.0.6</name>
      <display>9.0.5 ( &gt;= .NETStandard,Version=v2.1 )</display>
      <isAbstract>false</isAbstract>
      <sort-children>by-type-then-by-name</sort-children>
      <genericTypes />
      <isMapped>false</isMapped>
      <parentFolderId>46db1846-1f8c-46e3-9fd2-b0aa080432ed</parentFolderId>
      <packageId>5d8b794d-4032-489f-ac2b-8a73a23a6bf3</packageId>
      <packageName>Intent.EntityFrameworkCore.DesignTimeDbContextFactory</packageName>
      <stereotypes>
        <stereotype stereotypeDefinitionId="7af88c37-ce54-49fc-b577-bde869c23462" name="Package Version Settings">
          <addedByDefault>false</addedByDefault>
          <definitionPackageName>Intent.ModuleBuilder.CSharp</definitionPackageName>
          <definitionPackageId>f2bfb0f7-d304-466f-b923-021d4016b48d</definitionPackageId>
          <properties>
            <property name="b01cea92-0ca1-4dbe-acab-d0f52b39e003" display="Minimum Target Framework" value=".NETStandard,Version=v2.1" isActive="true" />
            <property name="d00692b1-6d17-4f1e-9386-a1d0d3ab7b57" display="Locked" value="false" isActive="true" />
          </properties>
        </stereotype>
      </stereotypes>
      <metadata />
      <childElements>
        <childElement id="dece0819-0269-4a20-ab39-e271748dd439" type="NuGet Dependency" typeId="3097322a-a058-4058-beed-4fcd6272f61d">
          <name>Microsoft.Extensions.Configuration.Abstractions</name>
          <isAbstract>false</isAbstract>
          <value>9.0.6</value>
          <genericTypes />
          <isMapped>false</isMapped>
          <parentFolderId>8e8418b0-e9a5-4113-80e9-931c19d72109</parentFolderId>
          <stereotypes />
          <metadata />
          <childElements />
        </childElement>
        <childElement id="f1f34278-bac4-451c-afae-665032ee03d0" type="NuGet Dependency" typeId="3097322a-a058-4058-beed-4fcd6272f61d">
          <name>Microsoft.Extensions.Configuration.FileExtensions</name>
          <isAbstract>false</isAbstract>
          <value>9.0.6</value>
          <genericTypes />
          <isMapped>false</isMapped>
          <parentFolderId>8e8418b0-e9a5-4113-80e9-931c19d72109</parentFolderId>
          <stereotypes />
          <metadata />
          <childElements />
        </childElement>
        <childElement id="36f5d470-1c75-4127-a346-09e661d66517" type="NuGet Dependency" typeId="3097322a-a058-4058-beed-4fcd6272f61d">
          <name>Microsoft.Extensions.Configuration</name>
          <isAbstract>false</isAbstract>
          <value>9.0.6</value>
          <genericTypes />
          <isMapped>false</isMapped>
          <parentFolderId>8e8418b0-e9a5-4113-80e9-931c19d72109</parentFolderId>
          <stereotypes />
          <metadata />
          <childElements />
        </childElement>
        <childElement id="ccc7789b-ec55-4006-b620-7b9aba0c0c06" type="NuGet Dependency" typeId="3097322a-a058-4058-beed-4fcd6272f61d">
          <name>Microsoft.Extensions.FileProviders.Abstractions</name>
          <isAbstract>false</isAbstract>
          <value>9.0.6</value>
          <genericTypes />
          <isMapped>false</isMapped>
          <parentFolderId>8e8418b0-e9a5-4113-80e9-931c19d72109</parentFolderId>
          <stereotypes />
          <metadata />
          <childElements />
        </childElement>
        <childElement id="23748e74-fe54-4e47-a6dd-28354a0db974" type="NuGet Dependency" typeId="3097322a-a058-4058-beed-4fcd6272f61d">
          <name>System.Text.Json</name>
          <isAbstract>false</isAbstract>
          <value>9.0.6</value>
          <genericTypes />
          <isMapped>false</isMapped>
          <parentFolderId>8e8418b0-e9a5-4113-80e9-931c19d72109</parentFolderId>
          <stereotypes />
          <metadata />
          <childElements />
        </childElement>
      </childElements>
    </childElement>
    <childElement id="e377da6d-94c0-41cf-8a99-a8be633d9c56" type="Package Version" typeId="231f8cf8-517b-4801-9682-991d22f4e662">
      <name>9.0.6</name>
      <display>9.0.5 ( &gt;= .NETCoreApp,Version=v9.0 )</display>
      <isAbstract>false</isAbstract>
      <sort-children>by-type-then-by-name</sort-children>
      <genericTypes />
      <isMapped>false</isMapped>
      <parentFolderId>46db1846-1f8c-46e3-9fd2-b0aa080432ed</parentFolderId>
      <packageId>5d8b794d-4032-489f-ac2b-8a73a23a6bf3</packageId>
      <packageName>Intent.EntityFrameworkCore.DesignTimeDbContextFactory</packageName>
      <stereotypes>
        <stereotype stereotypeDefinitionId="7af88c37-ce54-49fc-b577-bde869c23462" name="Package Version Settings">
          <addedByDefault>false</addedByDefault>
          <definitionPackageName>Intent.ModuleBuilder.CSharp</definitionPackageName>
          <definitionPackageId>f2bfb0f7-d304-466f-b923-021d4016b48d</definitionPackageId>
          <properties>
            <property name="b01cea92-0ca1-4dbe-acab-d0f52b39e003" display="Minimum Target Framework" value=".NETCoreApp,Version=v9.0" isActive="true" />
            <property name="d00692b1-6d17-4f1e-9386-a1d0d3ab7b57" display="Locked" value="false" isActive="true" />
          </properties>
        </stereotype>
      </stereotypes>
      <metadata />
      <childElements>
        <childElement id="859bde10-a506-4641-a4e7-81464bb3993b" type="NuGet Dependency" typeId="3097322a-a058-4058-beed-4fcd6272f61d">
          <name>Microsoft.Extensions.Configuration.Abstractions</name>
          <isAbstract>false</isAbstract>
          <value>9.0.6</value>
          <genericTypes />
          <isMapped>false</isMapped>
          <parentFolderId>e377da6d-94c0-41cf-8a99-a8be633d9c56</parentFolderId>
          <stereotypes />
          <metadata />
          <childElements />
        </childElement>
        <childElement id="3657d4ad-e3bf-47ca-af89-7b114503ef37" type="NuGet Dependency" typeId="3097322a-a058-4058-beed-4fcd6272f61d">
          <name>Microsoft.Extensions.Configuration.FileExtensions</name>
          <isAbstract>false</isAbstract>
          <value>9.0.6</value>
          <genericTypes />
          <isMapped>false</isMapped>
          <parentFolderId>e377da6d-94c0-41cf-8a99-a8be633d9c56</parentFolderId>
          <stereotypes />
          <metadata />
          <childElements />
        </childElement>
        <childElement id="0b070719-ba71-439f-84e7-34cbf3c2bd41" type="NuGet Dependency" typeId="3097322a-a058-4058-beed-4fcd6272f61d">
          <name>Microsoft.Extensions.Configuration</name>
          <isAbstract>false</isAbstract>
          <value>9.0.6</value>
          <genericTypes />
          <isMapped>false</isMapped>
          <parentFolderId>e377da6d-94c0-41cf-8a99-a8be633d9c56</parentFolderId>
          <stereotypes />
          <metadata />
          <childElements />
        </childElement>
        <childElement id="6ac6dbd0-3e27-4c60-b313-e350dedac62a" type="NuGet Dependency" typeId="3097322a-a058-4058-beed-4fcd6272f61d">
          <name>Microsoft.Extensions.FileProviders.Abstractions</name>
          <isAbstract>false</isAbstract>
          <value>9.0.6</value>
          <genericTypes />
          <isMapped>false</isMapped>
          <parentFolderId>e377da6d-94c0-41cf-8a99-a8be633d9c56</parentFolderId>
          <stereotypes />
          <metadata />
          <childElements />
        </childElement>
      </childElements>
    </childElement>
  </childElements>
</class>