<?xml version="1.0" encoding="utf-8"?>
<class id="3b7cb49a-005e-4b51-bffa-c7e290a73ae6" type="Factory Extension" typeId="7d008e84-bb28-4b10-ba28-7439202fca76">
  <name>ConfigureConventionsExtension</name>
  <display>ConfigureConventionsExtension</display>
  <isAbstract>false</isAbstract>
  <genericTypes />
  <isMapped>false</isMapped>
  <parentFolderId>a9d2a398-04e4-4300-9fbb-768568c65f9e</parentFolderId>
  <packageId>a9d2a398-04e4-4300-9fbb-768568c65f9e</packageId>
  <packageName>Intent.EntityFrameworkCore</packageName>
  <stereotypes />
  <metadata />
  <childElements />
</class>