<?xml version="1.0" encoding="utf-8"?>
<class id="a9e20efc-d775-407b-9350-df18e22a5311" type="Template Decorator" typeId="f0f46278-29ea-42bd-9206-0e7034f623bc">
  <name>ConsumerUnitOfWorkDecorator</name>
  <display>ConsumerUnitOfWorkDecorator: ConsumerDecorator</display>
  <isAbstract>false</isAbstract>
  <genericTypes />
  <typeReference id="254ad51e-e70e-4f2b-bba6-d9d17559752a">
    <typeId>dcbc9d8c-3261-4c3b-b6c6-f3da2dc7632c</typeId>
    <isNavigable>true</isNavigable>
    <isNullable>false</isNullable>
    <isCollection>false</isCollection>
    <isRequired>true</isRequired>
    <typePackageName>Intent.Eventing.MassTransit</typePackageName>
    <typePackageId>6502ee82-f515-4007-9635-bade3eb88e72</typePackageId>
    <stereotypes />
    <genericTypeParameters />
  </typeReference>
  <isMapped>false</isMapped>
  <parentFolderId>9247ee2e-371b-4a85-9f1a-be08221cbbb8</parentFolderId>
  <packageId>9247ee2e-371b-4a85-9f1a-be08221cbbb8</packageId>
  <packageName>Intent.Eventing.MassTransit.EntityFrameworkCore</packageName>
  <stereotypes />
  <metadata />
  <childElements />
</class>