<?xml version="1.0" encoding="utf-8"?>
<class id="916022f1-8375-4607-bdc0-8e15a738138f" type="Factory Extension" typeId="7d008e84-bb28-4b10-ba28-7439202fca76">
  <name>DaprRepoFactoryExtension</name>
  <display>DaprRepoFactoryExtension</display>
  <isAbstract>false</isAbstract>
  <genericTypes />
  <isMapped>false</isMapped>
  <parentFolderId>73923254-9ff4-4af0-b5a8-aba37165e9bc</parentFolderId>
  <packageId>73923254-9ff4-4af0-b5a8-aba37165e9bc</packageId>
  <packageName>Intent.Dapr.AspNetCore.StateManagement</packageName>
  <stereotypes />
  <metadata />
  <childElements />
</class>