<?xml version="1.0" encoding="utf-8"?>
<class id="a84ef5e8-2d37-4ba8-a1a2-e412a3404665" type="Solution Folder" typeId="0dc2b846-c968-49eb-99b7-8776919313a8">
  <name>3 - Domain</name>
  <display>3 - Domain</display>
  <isAbstract>false</isAbstract>
  <sort-children>by-type-then-by-name</sort-children>
  <genericTypes />
  <isMapped>false</isMapped>
  <parentFolderId>535c6cb4-5989-4f6a-9220-665334464fcc</parentFolderId>
  <packageId>535c6cb4-5989-4f6a-9220-665334464fcc</packageId>
  <packageName>${application.name}</packageName>
  <stereotypes />
  <metadata />
  <childElements />
</class>